fastrtps_cmake_module/_dummy.cpython-314-x86_64-linux-gnu.so
ros_fastrtps_cmake_module-3.6.2.data/data/share/ament_index/resource_index/package_run_dependencies/fastrtps_cmake_module
ros_fastrtps_cmake_module-3.6.2.data/data/share/ament_index/resource_index/packages/fastrtps_cmake_module
ros_fastrtps_cmake_module-3.6.2.data/data/share/ament_index/resource_index/parent_prefix_path/fastrtps_cmake_module
ros_fastrtps_cmake_module-3.6.2.data/data/share/fastrtps_cmake_module/local_setup.bash
ros_fastrtps_cmake_module-3.6.2.data/data/share/fastrtps_cmake_module/local_setup.dsv
ros_fastrtps_cmake_module-3.6.2.data/data/share/fastrtps_cmake_module/local_setup.sh
ros_fastrtps_cmake_module-3.6.2.data/data/share/fastrtps_cmake_module/local_setup.zsh
ros_fastrtps_cmake_module-3.6.2.data/data/share/fastrtps_cmake_module/package.dsv
ros_fastrtps_cmake_module-3.6.2.data/data/share/fastrtps_cmake_module/package.xml
ros_fastrtps_cmake_module-3.6.2.data/data/share/fastrtps_cmake_module/cmake/fastrtps_cmake_module-extras.cmake
ros_fastrtps_cmake_module-3.6.2.data/data/share/fastrtps_cmake_module/cmake/fastrtps_cmake_moduleConfig-version.cmake
ros_fastrtps_cmake_module-3.6.2.data/data/share/fastrtps_cmake_module/cmake/fastrtps_cmake_moduleConfig.cmake
ros_fastrtps_cmake_module-3.6.2.data/data/share/fastrtps_cmake_module/cmake/Modules/FindFastRTPS.cmake
ros_fastrtps_cmake_module-3.6.2.data/data/share/fastrtps_cmake_module/environment/ament_prefix_path.dsv
ros_fastrtps_cmake_module-3.6.2.data/data/share/fastrtps_cmake_module/environment/ament_prefix_path.sh
ros_fastrtps_cmake_module-3.6.2.data/data/share/fastrtps_cmake_module/environment/path.dsv
ros_fastrtps_cmake_module-3.6.2.data/data/share/fastrtps_cmake_module/environment/path.sh
ros_fastrtps_cmake_module-3.6.2.dist-info/METADATA
ros_fastrtps_cmake_module-3.6.2.dist-info/WHEEL
ros_fastrtps_cmake_module-3.6.2.dist-info/top_level.txt
ros_fastrtps_cmake_module-3.6.2.dist-info/RECORD
