Metadata-Version: 2.4
Name: ros-fastrtps-cmake-module
Version: 3.6.2
Summary: A ROS package providing a CMake module to easily find and integrate eProsima FastRTPS installations within other ROS packages.
Dynamic: description
Dynamic: description-content-type
Dynamic: summary
